{"cameraMode":{"drawMode":0,"name":"Shaded","section":"Shading Mode"},"sceneLighting":true,"audioPlay":false,"sceneViewState":{"m_AlwaysRefresh":false,"showFog":true,"showSkybox":true,"showFlares":true,"showImageEffects":true,"showParticleSystems":true,"showVisualEffectGraphs":true,"m_FxEnabled":true},"in2DMode":false,"pivot":{"x":-7.522287368774414,"y":-9.315186500549317,"z":-9.607422828674317},"rotation":{"x":-0.004315126687288284,"y":0.852876603603363,"z":-0.522064208984375,"w":-0.006784285418689251},"size":43.6676025390625,"orthographic":false}